sssekai/__gui__.py
sssekai/__init__.py
sssekai/__main__.py
sssekai/abcache/__init__.py
sssekai/abcache/auth.py
sssekai/abcache/fs.py
sssekai/crypto/APIManager.py
sssekai/crypto/AssetBundle.py
sssekai/crypto/__init__.py
sssekai/entrypoint/__init__.py
sssekai/entrypoint/abcache.py
sssekai/entrypoint/abdecrypt.py
sssekai/entrypoint/abserve.py
sssekai/entrypoint/apidecrypt.py
sssekai/entrypoint/apphash.py
sssekai/entrypoint/il2cpp.py
sssekai/entrypoint/live2dextract.py
sssekai/entrypoint/moc3paths.py
sssekai/entrypoint/mvdata.py
sssekai/entrypoint/rla2json.py
sssekai/entrypoint/spineextract.py
sssekai/entrypoint/usmdemux.py
sssekai/fmt/__init__.py
sssekai/fmt/moc3.py
sssekai/fmt/motion3.py
sssekai/fmt/rla.py
sssekai/generated/__init__.py
sssekai/generated/Sekai/__init__.py
sssekai/unity/AnimationClip.py
sssekai/unity/AssetBundle.py
sssekai/unity/__init__.py
sssekai/unity/constant/SekaiLive2DPathNames.py
sssekai/unity/constant/__init__.py
sssekai-0.7.62.dist-info/licenses/LICENSE
tests/__init__.py
tests/_test_abcache.py
tests/test_apphash.py
tests/test_legacy_anim.py
tests/test_live2d.py
tests/test_rla.py
tests/test_spine.py
sssekai-0.7.62.dist-info/METADATA
sssekai-0.7.62.dist-info/WHEEL
sssekai-0.7.62.dist-info/entry_points.txt
sssekai-0.7.62.dist-info/top_level.txt
sssekai-0.7.62.dist-info/RECORD
