Metadata-Version: 2.4
Name: sssekai
Version: 0.7.62
Summary: Project SEKAI Asset Utility / PJSK 资源工具
Home-page: https://github.com/mos9527/sssekai
Author: greats3an
Author-email: greats3an@gmail.com
Classifier: Programming Language :: Python :: 3
Classifier: License :: OSI Approved :: MIT License
Classifier: Operating System :: OS Independent
Requires-Python: >=3.10
License-File: LICENSE
Requires-Dist: msgpack
Requires-Dist: requests
Requires-Dist: pycryptodome
Requires-Dist: unitypy>=1.23.0
Requires-Dist: tqdm
Requires-Dist: coloredlogs
Provides-Extra: gui
Requires-Dist: GooeyEx>=0.0.8; extra == "gui"
Provides-Extra: il2cpp
Requires-Dist: lief; extra == "il2cpp"
Provides-Extra: criware
Requires-Dist: PyCriCodecsEx; extra == "criware"
Dynamic: author
Dynamic: author-email
Dynamic: classifier
Dynamic: description
Dynamic: description-content-type
Dynamic: home-page
Dynamic: license-file
Dynamic: provides-extra
Dynamic: requires-dist
Dynamic: requires-python
Dynamic: summary
